dbt/adapters/athena/__init__.py
dbt/adapters/athena/__version__.py
dbt/adapters/athena/connections.py
dbt/adapters/athena/impl.py
dbt/adapters/athena/query_headers.py
dbt/adapters/athena/relation.py
dbt/include/athena/__init__.py
dbt/include/athena/dbt_project.yml
dbt/include/athena/profile_template.yml
dbt/include/athena/sample_profiles.yml
dbt/include/athena/macros/adapters/columns.sql
dbt/include/athena/macros/adapters/freshness.sql
dbt/include/athena/macros/adapters/metadata.sql
dbt/include/athena/macros/adapters/relation.sql
dbt/include/athena/macros/materializations/models/helpers.sql
dbt/include/athena/macros/materializations/models/incremental/helpers.sql
dbt/include/athena/macros/materializations/models/incremental/incremental.sql
dbt/include/athena/macros/materializations/models/table/create_table_as.sql
dbt/include/athena/macros/materializations/models/table/table.sql
dbt/include/athena/macros/materializations/models/view/create_or_replace_view.sql
dbt/include/athena/macros/materializations/models/view/create_view_as.sql
dbt/include/athena/macros/materializations/models/view/view.sql
dbt/include/athena/macros/materializations/seeds/helpers.sql
dbt/include/athena/macros/materializations/snapshots/snapshot.sql
dbt_athena_adapter-1.0.1.dist-info/LICENSE.txt
dbt_athena_adapter-1.0.1.dist-info/METADATA
dbt_athena_adapter-1.0.1.dist-info/WHEEL
dbt_athena_adapter-1.0.1.dist-info/top_level.txt
dbt_athena_adapter-1.0.1.dist-info/RECORD
