Metadata-Version: 2.1
Name: dbt-athena-adapter
Version: 1.0.1
Summary: The athena adapter plugin for dbt (data build tool)
Home-page: https://github.com/Tomme/dbt-athena
Author: Thomas Elvey
Author-email: tomelvey@googlemail.com
License-File: LICENSE.txt
Requires-Dist: dbt-core (>=1.0.1)
Requires-Dist: pyathena (>=2.2.0)
Requires-Dist: boto3 (>=1.18.12)
Requires-Dist: tenacity (>=6.3.1)
